muso/__init__.py
muso/application.py
muso/auth.py
muso/errors.py
muso/request.py
muso/response.py
muso/route.py
muso/run.py
muso/schema.py
muso/utils.py
muso/cli/__init__.py
muso/mysql/__init__.py
muso/postgres/__init__.py
muso/redis/__init__.py
muso/valkey/__init__.py
muso-0.0.1a78.dist-info/licenses/LICENSE
muso-0.0.1a78.dist-info/METADATA
muso-0.0.1a78.dist-info/WHEEL
muso-0.0.1a78.dist-info/top_level.txt
muso-0.0.1a78.dist-info/RECORD
