Metadata-Version: 2.4
Name: muso
Version: 0.0.1a78
Summary: A simple async JSON API-Framework based on Marshmallow / Uvicorn / Starlette / Orjson.
Author-email: "M@gicAgCl(DEAD)" <wyqsmith@aegeanstudio.com>
Requires-Python: >=3.12
License-File: LICENSE
Requires-Dist: apispec
Requires-Dist: marshmallow<4
Requires-Dist: orjson
Requires-Dist: python-multipart
Requires-Dist: starlette<1.0.0
Requires-Dist: tzlocal
Requires-Dist: uvicorn
Provides-Extra: uvicorn-standard
Requires-Dist: uvicorn[standard]; extra == "uvicorn-standard"
Requires-Dist: uvloop; platform_system != "Windows" and extra == "uvicorn-standard"
Provides-Extra: mysql
Requires-Dist: aiomysql; extra == "mysql"
Provides-Extra: postgres
Requires-Dist: psycopg[binary,pool]; extra == "postgres"
Provides-Extra: redis
Requires-Dist: redis[hiredis]; extra == "redis"
Provides-Extra: valkey
Requires-Dist: valkey[libvalkey]; extra == "valkey"
Dynamic: license-file
